xj_resource/__init__.py
xj_resource/admin.py
xj_resource/apps.py
xj_resource/config.py
xj_resource/models.py
xj_resource/urls.py
xj_resource/apis/__init__.py
xj_resource/apis/resource_file_list.py
xj_resource/apis/resource_image_list.py
xj_resource/apis/resource_upload_file.py
xj_resource/apis/resource_upload_image.py
xj_resource/apis/resource_upload_video.py
xj_resource/apis/resource_video_list.py
xj_resource/services/__init__.py
xj_resource/services/resource_file_service.py
xj_resource/services/resource_image_service.py
xj_resource/services/resource_oss_service.py
xj_resource/services/resource_upload_service.py
xj_resource/services/resource_video_service.py
xj_resource/services/upload_file_service [赵向明2022.8.26以前].py
xj_resource/services/upload_file_service [赵向明7.31以前].py
xj_resource/services/upload_image_service [赵向明7.31以前].py
xj_resource/utils/__init__.py
xj_resource/utils/check_type.py
xj_resource/utils/custom_response.py
xj_resource/utils/custom_tool.py
xj_resource/utils/digit_algorithm.py
xj_resource/utils/excel_operate.py
xj_resource/utils/file_operate.py
xj_resource/utils/j_config.py
xj_resource/utils/j_dict.py
xj_resource/utils/j_ulid_field.py
xj_resource/utils/model_handle.py
xj_resource/utils/validate.py
xj_resource-1.3.1.dist-info/METADATA
xj_resource-1.3.1.dist-info/WHEEL
xj_resource-1.3.1.dist-info/top_level.txt
xj_resource-1.3.1.dist-info/RECORD
