Metadata-Version: 2.1
Name: xj-resource
Version: 1.3.1
Summary: 资源模块
Home-page: UNKNOWN
License: apache 3.0
Platform: UNKNOWN
